alexa_skill/__init__.py
alexa_skill/dates.py
alexa_skill/messages.py
alexa_skill/intents/__init__.py
alexa_skill/intents/base.py
alexa_skill/intents/buildins.py
alexa_skill/tests/__init__.py
alexa_skill/tests/test_alexa_dates.py
alexa_skill/tests/test_messages.py
alexa_skill-0.1.0.dist-info/LICENSE.txt
alexa_skill-0.1.0.dist-info/METADATA
alexa_skill-0.1.0.dist-info/RECORD
alexa_skill-0.1.0.dist-info/WHEEL
alexa_skill-0.1.0.dist-info/top_level.txt
examples/__init__.py
examples/falcon_app/__init__.py
examples/falcon_app/main.py
examples/falcon_app/tests.py
examples/flask_app/__init__.py
examples/flask_app/main.py
examples/flask_app/tests.py
