Metadata-Version: 2.1
Name: alexa-skill
Version: 0.1.0
Summary: A flexible and easy-to-use package for building Alexa skill applications.
Home-page: https://github.com/stanwood/alexa-skill
Author: stanwood GmbH
Author-email: piotr.rogulski@stanwood.de,developer@stanwood.io
License: UNKNOWN
Platform: UNKNOWN
Classifier: Programming Language :: Python :: 2
Classifier: License :: OSI Approved :: MIT License
Classifier: Operating System :: OS Independent
Provides-Extra: docs
Provides-Extra: dev
Requires-Dist: python-dateutil (==2.7.3)
Provides-Extra: dev
Requires-Dist: pytest; extra == 'dev'
Requires-Dist: coverage; extra == 'dev'
Requires-Dist: tox; extra == 'dev'
Requires-Dist: sphinx; extra == 'dev'
Requires-Dist: sphinx-rtd-theme; extra == 'dev'
Provides-Extra: docs
Requires-Dist: sphinx; extra == 'docs'
Requires-Dist: sphinx-autobuild; extra == 'docs'
Requires-Dist: sphinx-rtd-theme; extra == 'docs'
